cockatoo/__init__.py
cockatoo/cockatoo.py
cockatoo/config/template_coassemble.yaml
cockatoo/config/template_evaluate.yaml
cockatoo/workflow/coassemble.smk
cockatoo/workflow/evaluate.smk
cockatoo/workflow/env/aviary.yml
cockatoo/workflow/env/coverm.yml
cockatoo/workflow/env/prodigal.yml
cockatoo/workflow/env/r.yml
cockatoo/workflow/env/singlem.yml
cockatoo/workflow/scripts/aviary_commands.py
cockatoo/workflow/scripts/cluster_graph.py
cockatoo/workflow/scripts/collect_reference_bins.py
cockatoo/workflow/scripts/evaluate.py
cockatoo/workflow/scripts/query_processing.py
cockatoo/workflow/scripts/separate_SingleM_seq.py
cockatoo/workflow/scripts/single_assembly.py
cockatoo/workflow/scripts/summarise_coassemblies.py
cockatoo/workflow/scripts/target_elusive.py
cockatoo_genome-0.4.8.dist-info/LICENSE
cockatoo_genome-0.4.8.dist-info/METADATA
cockatoo_genome-0.4.8.dist-info/WHEEL
cockatoo_genome-0.4.8.dist-info/entry_points.txt
cockatoo_genome-0.4.8.dist-info/top_level.txt
cockatoo_genome-0.4.8.dist-info/RECORD
