Metadata-Version: 2.1
Name: cockatoo-genome
Version: 0.4.8
Summary: Cockatoo - intelligent clustering of metagenomic samples for coassembly
Author-email: Samuel Aroney <samuel.aroney@outlook.com>
License: GNU GENERAL PUBLIC LICENSE
Project-URL: Homepage, https://github.com/AroneyS/cockatoo
Project-URL: Bug Tracker, https://github.com/AroneyS/cockatoo/issues
Classifier: Topic :: Scientific/Engineering :: Bio-Informatics
Requires-Python: >=3.7
License-File: LICENSE
Requires-Dist: snakemake (>=6.0.5)
Requires-Dist: pandas
Requires-Dist: biopython
Requires-Dist: networkx
Requires-Dist: bird-tool-utils
Requires-Dist: extern
Requires-Dist: ruamel.yaml (>=0.15.99)
